setup.py
scales_datadog/__init__.py
scales_datadog/datadog.py
scales_datadog.egg-info/PKG-INFO
scales_datadog.egg-info/SOURCES.txt
scales_datadog.egg-info/dependency_links.txt
scales_datadog.egg-info/requires.txt
scales_datadog.egg-info/top_level.txt