Metadata-Version: 1.0
Name: scales-datadog
Version: 0.5.3
Summary: A pusher class to send metrics collected by scales to datadog
Home-page: https://www.github.com/tbarbugli/scales_datadog
Author: Tommaso Barbugli
Author-email: tbarbugli@gmail.com
License: BSD
Platform: UNKNOWN
Classifier: Intended Audience :: Developers
Classifier: Intended Audience :: System Administrators
Classifier: Operating System :: OS Independent
Classifier: Topic :: Software Development
Classifier: Development Status :: 5 - Production/Stable
Classifier: License :: OSI Approved :: GNU General Public License (GPL)
Classifier: Natural Language :: English
Classifier: Programming Language :: Python
Classifier: Topic :: Scientific/Engineering :: Mathematics
Classifier: Topic :: Software Development :: Libraries :: Python Modules
